LICENSE
README.md
setup.py
yummy/__init__.py
yummy/cli.py
yummy.egg-info/PKG-INFO
yummy.egg-info/SOURCES.txt
yummy.egg-info/dependency_links.txt
yummy.egg-info/entry_points.txt
yummy.egg-info/requires.txt
yummy.egg-info/top_level.txt
yummy/backends/__init__.py
yummy/backends/backend.py
yummy/backends/dask.py
yummy/backends/polars.py
yummy/backends/spark.py
yummy/providers/__init__.py
yummy/providers/provider.py
yummy/registries/__init__.py
yummy/registries/registry.py
yummy/sources/__init__.py
yummy/sources/delta.py
yummy/sources/file.py
yummy/sources/iceberg.py
yummy/sources/source.py