Metadata-Version: 2.1
Name: yummy
Version: 0.0.9
Summary: UNKNOWN
Home-page: https://github.com/yummyml/yummy
Author: Qooba
License: Apache License, Version 2.0
Keywords: feast featurestore polars dask ray pyspark offlinestore
Platform: UNKNOWN
Classifier: License :: OSI Approved :: Apache Software License
Classifier: Programming Language :: Python
Classifier: Programming Language :: Python :: 3
Classifier: Programming Language :: Python :: 3.7
Classifier: Programming Language :: Python :: 3.8
Classifier: Programming Language :: Python :: 3.9
Requires-Python: >=3.7.0
Provides-Extra: dask
Provides-Extra: delta
Provides-Extra: dev
Provides-Extra: feast
Provides-Extra: features
Provides-Extra: mlflow
Provides-Extra: ray
Provides-Extra: spark
